magpylib_material_response/__init__.py
magpylib_material_response/demag.py
magpylib_material_response/meshing.py
magpylib_material_response/meshing_utils.py
magpylib_material_response/polyline.py
magpylib_material_response/utils.py
magpylib_material_response/data/__init__.py
magpylib_material_response/package_data/datasets/FEMdata_test_cuboids.json
magpylib_material_response/package_data/datasets/FEMdata_test_softmag.json
tests/__init__.py
tests/test_basic.py
tests/test_isotropic_anisotropic.py
tests/test_meshing.py
magpylib_material_response-0.3.0.dist-info/LICENSE
magpylib_material_response-0.3.0.dist-info/METADATA
magpylib_material_response-0.3.0.dist-info/WHEEL
magpylib_material_response-0.3.0.dist-info/top_level.txt
magpylib_material_response-0.3.0.dist-info/RECORD
