Metadata-Version: 2.1
Name: magpylib-material-response
Version: 0.3.0
Summary: An extension to the Magpylib library, providing magnetic field analysis for soft materials and demagnetization of hard magnets.
Home-page: https://github.com/magpylib/magpylib-material-response
Author: Alexandre Boisselet
Author-email: magpylib@gmail.com
License: MIT
Platform: UNKNOWN
Classifier: Development Status :: 2 - Pre-Alpha
Classifier: License :: OSI Approved :: MIT License
Classifier: Programming Language :: Python :: 3
Classifier: Topic :: Software Development :: Libraries :: Python Modules
License-File: LICENSE
Requires-Dist: magpylib>=5.0
Requires-Dist: loguru
Provides-Extra: code_style
Requires-Dist: flake8; extra == "code-style"
Requires-Dist: black; extra == "code-style"
Requires-Dist: pre-commit; extra == "code-style"
Provides-Extra: docs
Requires-Dist: urllib3<2.0; extra == "docs"
Requires-Dist: sphinx; extra == "docs"
Requires-Dist: sphinx-book-theme; extra == "docs"
Requires-Dist: sphinx-copybutton; extra == "docs"
Requires-Dist: sphinx-design; extra == "docs"
Requires-Dist: myst-nb; extra == "docs"
Requires-Dist: plotly; extra == "docs"
Requires-Dist: pandas; extra == "docs"
Provides-Extra: testing
Requires-Dist: pytest; extra == "testing"
